pyasmtools/__init__.py
pyasmtools/prettydiasm.py
pyasmtools/prettytrace.py
pyasmtools-1.0.4.dist-info/LICENSE.txt
pyasmtools-1.0.4.dist-info/METADATA
pyasmtools-1.0.4.dist-info/WHEEL
pyasmtools-1.0.4.dist-info/top_level.txt
pyasmtools-1.0.4.dist-info/RECORD
