Metadata-Version: 2.1
Name: pyasmtools
Version: 1.0.4
Summary: a python bytecode disassembler and execution tracer, all done as decorators.
Home-page: https://github.com/MoserMichael/pyasmtools
Author: Michael Moser
Author-email: moser.michael@gmail.com
License: MIT
Keywords: utility
Platform: UNKNOWN
Classifier: Programming Language :: Python :: 3
Classifier: License :: OSI Approved :: MIT License
Classifier: Operating System :: OS Independent
Classifier: Topic :: Software Development :: Debuggers
Requires-Python: >=3.6
